polars_gps_hilbert-0.1.1.dist-info/METADATA
polars_gps_hilbert-0.1.1.dist-info/WHEEL
polars_gps_hilbert-0.1.1.dist-info/licenses/LICENSE
polars_gps_hilbert/__init__.py
polars_gps_hilbert/_polars_gps_hilbert.pyd
polars_gps_hilbert-0.1.1.dist-info/RECORD
