Metadata-Version: 2.4
Name: polars-gps-hilbert
Version: 0.1.1
Classifier: Development Status :: 3 - Alpha
Classifier: Intended Audience :: Developers
Classifier: Programming Language :: Rust
Classifier: Programming Language :: Python :: Implementation :: CPython
Classifier: Programming Language :: Python :: Implementation :: PyPy
Requires-Dist: maturin>=1.8.6
Requires-Dist: numpy>=1.24.4
Requires-Dist: polars>=1.30.0
Requires-Dist: psutil>=7.0.0
Requires-Dist: pytest>=8.3.5
Requires-Dist: pytest-benchmark>=4.0.0 ; extra == 'dev'
Requires-Dist: pandas>=2.0.0 ; extra == 'dev'
Provides-Extra: dev
License-File: LICENSE
Summary: ⚠️ EXPERIMENTAL: High-performance Polars plugin for GPS trajectory indexing using 3D Hilbert curves. Not for production use.
Requires-Python: >=3.9
